<?xml version="1.0" encoding="UTF-8"?><REUTERS CGISPLIT="TRAINING-SET" LEWISSPLIT="TRAIN" NEWID="14077" OLDID="3060" TOPICS="NO">
<DATE> 7-APR-1987 11:22:43.79</DATE>
<TOPICS/>
<PLACES><D>usa</D></PLACES>
<PEOPLE/>
<ORGS/>
<EXCHANGES/>
<COMPANIES/>
<UNKNOWN> 
   F
   f1241 reute
r f BC-PRESIDENTIAL-AIR-&lt;PAI   04-07 0091</UNKNOWN>
<TEXT> 
<TITLE>PRESIDENTIAL AIR &lt;PAIR&gt; IN SALE/LEASEBACK</TITLE>
<DATELINE>    WASHINGTON, April 7 - </DATELINE><BODY>Presidential Airways Inc saiud it has
sold 10 of its 11 Boeing 737's to Ryder System Inc &lt;RDR&gt;, which
then leased seven of the planes Boeing Co &lt;BA&gt; made planes back
to Presidential on a short-term basis.
    The company said it ended long-term leases on the planes.
The short-term leases will run up to eight months and the
aircraft will be returned to Ryder on completion of present
charter commitments, coincinding with the expected deliveries
of British Aerospace Bae146 jets.
    In Miami, Ryder said it will sell the three planes that
Presidedntial will not lease back to other airlines.
 Reuter
 </BODY></TEXT>
</REUTERS>