<?xml version="1.0" encoding="UTF-8"?><REUTERS CGISPLIT="TRAINING-SET" LEWISSPLIT="TRAIN" NEWID="14216" OLDID="3199" TOPICS="BYPASS">
<DATE> 7-APR-1987 12:02:22.99</DATE>
<TOPICS/>
<PLACES/>
<PEOPLE/>
<ORGS/>
<EXCHANGES/>
<COMPANIES/>
<UNKNOWN> 
   C G L M T RM
   f1426 reute
b f BC-LONDON-DOLLAR-CROSS-R   04-07 0089</UNKNOWN>
<TEXT TYPE="UNPROC"> 
LONDON DOLLAR CROSS RATES CLOSING - APRIL 7
      SPOT           1 MONTH      3 MONTHS     6 MONTHS
 STG 1.6185/95       52/49        133/128      228/223
 DMK 1.8240/50       42/39        122/117      247/242
 SFR 1.5120/30       48/43        114/109      228/218
 DFL 2.0575/85       19/16        58/53        130/125
 BFC 37.73/78        01/04        03/08        09/16
 FFR 6.0650/0700     85/105       240/270      465/515
 LIT 1299/1300       310/360      900/1100     1800/2300
 YEN 145.25/35       34/30        98/93        200/190
 CAN     1.3050/55
 BFR     37.90/93
 DKR     6.8750/8800
 NKR     6.8225/75
 SKR     6.3500/50
 AUS SCH 12.81/83
 HK      7.8012/17
 IRL     1.4650/70
 

</TEXT>
</REUTERS>