<?xml version="1.0" encoding="UTF-8"?><REUTERS CGISPLIT="TRAINING-SET" LEWISSPLIT="TEST" NEWID="14948" OLDID="3931" TOPICS="NO">
<DATE> 8-APR-1987 08:46:20.98</DATE>
<TOPICS/>
<PLACES><D>usa</D></PLACES>
<PEOPLE/>
<ORGS/>
<EXCHANGES/>
<COMPANIES/>
<UNKNOWN> 
   F
   f0788 reute
d f BC-&lt;ASIX-SYSTEMS&gt;-GETS-M   04-08 0085</UNKNOWN>
<TEXT> 
<TITLE>&lt;ASIX SYSTEMS&gt; GETS MORE FINANCING</TITLE>
<DATELINE>    FREMONT, Calif., April 8 - </DATELINE><BODY>ASIX Systems, a developer of
test systems for ASIC devices, said it has received 4,800,000
dlrs in a second round of equity financing.
    The company said investors include first round participants
Paragon Partners, Citicorp &lt;CCI&gt;, Vista Ventures, Rust Ventures
and Orien Ventures, plus new investors North Carolina Bank
Venture Co LP, RepublicBankCorp &lt;RPT&gt; and ECI Ventures.
    It said it has now raised total capitalization of 8,600,000
dlrs.
 Reuter
 </BODY></TEXT>
</REUTERS>