<?xml version="1.0" encoding="UTF-8"?><REUTERS CGISPLIT="TRAINING-SET" LEWISSPLIT="TRAIN" NEWID="7413" OLDID="12326" TOPICS="YES">
<DATE>19-MAR-1987 16:11:25.65</DATE>
<TOPICS><D>earn</D></TOPICS>
<PLACES><D>usa</D></PLACES>
<PEOPLE/>
<ORGS/>
<EXCHANGES/>
<COMPANIES/>
<UNKNOWN> 
   F
   f2376 reute
s f BC-JP-STEVENS-AND-CO-INC   03-19 0023</UNKNOWN>
<TEXT> 
<TITLE>JP STEVENS AND CO INC &lt;STN&gt; SETS PAYOUT</TITLE>
<DATELINE>    NEW YORK, March 19 -
    </DATELINE><BODY>Qtrly div 30 cts vs 30 cts prior
    Pay April 30
    Record April 3
 Reuter
 </BODY></TEXT>
</REUTERS>