<?xml version="1.0" encoding="UTF-8"?><REUTERS CGISPLIT="TRAINING-SET" LEWISSPLIT="TRAIN" NEWID="7654" OLDID="13175" TOPICS="YES">
<DATE>20-MAR-1987 09:34:18.67</DATE>
<TOPICS/>
<PLACES><D>canada</D></PLACES>
<PEOPLE/>
<ORGS/>
<EXCHANGES/>
<COMPANIES/>
<UNKNOWN> 
   E F
   f0847 reute
r f BC-rayrock   03-20 0089</UNKNOWN>
<TEXT> 
<TITLE>RAYROCK TO ISSUE 24 MLN DLRS OF NOTES</TITLE>
<DATELINE>    TORONTO, March 20 - </DATELINE><BODY>&lt;Rayrock Yellowknife Resources Inc&gt;
said it plans to sell 24 mln dlrs of convertible subordinated
notes by way of a private placement through First Marathon
Securities Ltd.
    The notes will be convertible into 7.5 pct convertible
subordinated debentures, which in turn will be convertible into
2.4 mln subordinate voting shares of the company.
    Rayrock said it expects to complete the note sale on April
nine. The sale is subject to regulatory approvals.
             
 Reuter
 </BODY></TEXT>
</REUTERS>