<?xml version="1.0" encoding="UTF-8"?><REUTERS CGISPLIT="TRAINING-SET" LEWISSPLIT="TRAIN" NEWID="10248" OLDID="15769" TOPICS="NO">
<DATE>26-MAR-1987 18:39:07.48</DATE>
<TOPICS/>
<PLACES><D>usa</D><D>canada</D></PLACES>
<PEOPLE/>
<ORGS/>
<EXCHANGES/>
<COMPANIES/>
<UNKNOWN> 
   E F
   f2869 reute
r f BC-BCE-DEVELOPMENT-TO-BU   03-26 0102</UNKNOWN>
<TEXT> 
<TITLE>BCE DEVELOPMENT TO BUILD STORE IN MINNEAPOLIS</TITLE>
<DATELINE>    VANCOUVER, British Columbia, March 26 - </DATELINE><BODY>&lt;BCE Development
Corp&gt; said its BCE Development Properties Inc U.S. unit agreed
with Saks Fifth Avenue and the city of Minneapolis, Minnesota
to build a four-level Saks store in downtown Minneapolis.
    The city will acquire the mall site from BCE Development,
which will then lease it back from the city. The city will also
subsidize an adjoining five-level 125,000 square foot retail
development, said BCE Development Corp, 68 pct-owned by Bell
Canada Enterprises Inc &lt;BCE&gt;.
    Other financial terms were undisclosed.
 Reuter
 </BODY></TEXT>
</REUTERS>