<?xml version="1.0" encoding="UTF-8"?><REUTERS CGISPLIT="TRAINING-SET" LEWISSPLIT="TRAIN" NEWID="13407" OLDID="2390" TOPICS="BYPASS">
<DATE> 7-APR-1987 04:15:24.80</DATE>
<TOPICS/>
<PLACES/>
<PEOPLE/>
<ORGS/>
<EXCHANGES/>
<COMPANIES/>
<UNKNOWN> 
   RM M
   f0159 reute
r f BC-TOKYO-GOLD-FUTURES-CL   04-07 0076</UNKNOWN>
<TEXT> 
<TITLE>TOKYO GOLD FUTURES CLOSE MOSTLY EASIER</TITLE>
<DATELINE>    TOKYO, April 7 - </DATELINE><BODY>Yen-denominated gold futures closed down
three to 10 yen per gramme following the lower New York market
except distant December which was unchanged, dealers said.
    Trading in gold was featureless as most speculators'
interest shifted to silver which has risen in line with the
higher New York market.
    International bullion was 421.90/422.40 dlrs an ounce
aginst 418.10/60 in New York.
 REUTER
 </BODY></TEXT>
</REUTERS>