<?xml version="1.0" encoding="UTF-8"?><REUTERS CGISPLIT="TRAINING-SET" LEWISSPLIT="TRAIN" NEWID="13512" OLDID="2495" TOPICS="YES">
<DATE> 7-APR-1987 07:05:55.60</DATE>
<TOPICS><D>money-fx</D><D>dlr</D></TOPICS>
<PLACES><D>west-germany</D></PLACES>
<PEOPLE/>
<ORGS/>
<EXCHANGES/>
<COMPANIES/>
<UNKNOWN> 
   RM
   f0403 reute
b f BC-NO-INTERVENTION,-DOLL   04-07 0032</UNKNOWN>
<TEXT> 
<TITLE>NO INTERVENTION, DOLLAR FIXED AT 1.8218 MARKS</TITLE>
<DATELINE>    FRANKFURT, April 7 - </DATELINE><BODY>The Bundesbank did not intervene as
the dollar was fixed lower at 1.8218 marks after 1.8243
yesterday, dealers said.
 REUTER
 </BODY></TEXT>
</REUTERS>