<?xml version="1.0" encoding="UTF-8"?><REUTERS CGISPLIT="TRAINING-SET" LEWISSPLIT="TRAIN" NEWID="13848" OLDID="2831" TOPICS="BYPASS">
<DATE> 7-APR-1987 10:11:56.57</DATE>
<TOPICS/>
<PLACES/>
<PEOPLE/>
<ORGS/>
<EXCHANGES/>
<COMPANIES/>
<UNKNOWN> 
   GQ
   f0933 reute
u f BC-mwest-hilos-precip   04-07 0114</UNKNOWN>
<TEXT TYPE="UNPROC"> 
MIDWEST HIGH-LOWS AND PRECIPITATION-APRIL 7
    HIGHEST TEMPERATURE YESTERDAY, LOWEST TEMPERATURE LAST 12
HOURS. PRECIPITATION FOR 24-HOURS ENDING 0600 HRS CST.
    ILLINOIS                WISCONSIN
 CHICAGO    60 36       MILWAUKEE   54 41     
 DECATUR    59 40 .02   MADISON     64 33     
 PEORIA     66 39       LACROSSE    70 37     
 QUINCY     57 38          INDIANA
 ROCKFORD   66 29       EVANSVILLE  50 44 t   
     IOWA               INDPLS      51 41 t   
 DES MOINES 67 36       FT WAYNE    53 44 t   
 SPENCER    69 n/a      SOUTH BEND  59 38     
 WATERLOO   67 34       LAFAYETTE   58 43 t   
 BURLINGTON 66 35       TERRE HAUTE 54 42 t   
    IOWA (CONTINUED)    MISSOURI
 CEDAR RAPIDS 66 34      KIRKSVILLE 58 38     
 DUBUQUE      64 40      ST JOSEPH  n/a       
 SIOUX CITY   66 33      KANSAS CTY 56 37     
     MICHIGAN            COLUMBIA   54 37     
 ALPENA       64 36      ST LOUIS   55 44 t   
 DETROIT      53 46 .03  JOPLIN     57 40     
 FLINT        56 37      SPRINGFLD  55 42 .02 
 GRAND RAPIDS 63 39      VICHY      53 42 t   
 LANSING      60 37      MONETT     53 40 t   
 PELLSTON     64 30      W PLAINS   n/a       
 SAGINAW      58 38      NORTH DAKOTA
 S.S. MARIE   65 35      BISMARK   66 31      
 TRAVERSE CTY 59 28      FARGO     71 32      
   SOUTH DAKOTA           NO DAKOTA (CONT)
 ABERDEEN   69 31      GRAND FORKS  67 33     
 HURON      70 34      MINOT        66 41     
 PIERRE     67 35        NEBRASKA
 RAPID CITY 64 30      GRAND ISL    60 33     
 SIOUX FLS  67 30      LINCOLN      63 31     
   KANSAS              NORFOLK      64 32     
 DODGE CITY 57 42      OMAHA        61 41     
 RUSSELL    53 40      VALENTINE    64 24     
 HUTCHINSON 54 46        MINNESOTA
 WICHITA    55 43      ALEXANDRIA   70 39     
 CONCORDIA  55 38      MPLS/ST.PAUL 70 36     
 TOPEKA     55 38 t    ROCHESTER    66 35     
 BELOIT     56 39      ST CLOUD     70 34     
 Reuter
 

</TEXT>
</REUTERS>