<?xml version="1.0" encoding="UTF-8"?><REUTERS CGISPLIT="TRAINING-SET" LEWISSPLIT="TRAIN" NEWID="13886" OLDID="2869" TOPICS="NO">
<DATE> 7-APR-1987 10:21:50.83</DATE>
<TOPICS/>
<PLACES><D>usa</D></PLACES>
<PEOPLE/>
<ORGS/>
<EXCHANGES/>
<COMPANIES/>
<UNKNOWN> 
   F
   f0983 reute
d f BC-COGNITIVE-&lt;CSAI&gt;-COMP   04-07 0087</UNKNOWN>
<TEXT> 
<TITLE>COGNITIVE &lt;CSAI&gt; COMPLETES WORK ON PROGRAM</TITLE>
<DATELINE>    NEW HAVEN, Conn., april 7 - </DATELINE><BODY>Cognitive Systems Inc said it
has completed work on a prototype artificial intelligence
program for American Express Co's &lt;AXP&gt; American Express travel
Related Services Inc involving a point-of-sale application for
customer-assisted transactions.
    The company said it developed the prototype under a fixed
price agreement on a one-tim project basis.  It said American
Express plans to conduct consumer testing of the program in the
near future.
 Reuter
 </BODY></TEXT>
</REUTERS>