<?xml version="1.0" encoding="UTF-8"?><REUTERS CGISPLIT="TRAINING-SET" LEWISSPLIT="TRAIN" NEWID="13923" OLDID="2906" TOPICS="BYPASS">
<DATE> 7-APR-1987 10:33:10.47</DATE>
<TOPICS/>
<PLACES/>
<PEOPLE/>
<ORGS/>
<EXCHANGES/>
<COMPANIES/>
<UNKNOWN> 
   MQ
   f1030 reute
u f BC-CBT-SILVER-10-30-EDT   04-07 0036</UNKNOWN>
<TEXT TYPE="UNPROC"> 
CBT SILVER 10:30 EDT
1,000 OUNCE
 APR7  6640 UP  70
 MAY7  6680 UP  80
 JUN7  6720 UP  80
 AUG7  6810 UP  90
 OCT7  6880 UP  80
 DEC7  6980 UP  100
 FEB8  7080 UP  120
 APR8  7150 UP  110
 JUN8  7250 UP  130
 AUG8 UNTRD
 

</TEXT>
</REUTERS>