<?xml version="1.0" encoding="UTF-8"?><REUTERS CGISPLIT="TRAINING-SET" LEWISSPLIT="TRAIN" NEWID="11974" OLDID="202" TOPICS="YES">
<DATE> 1-APR-1987 10:44:25.58</DATE>
<TOPICS/>
<PLACES><D>usa</D></PLACES>
<PEOPLE/>
<ORGS/>
<EXCHANGES/>
<COMPANIES/>
<UNKNOWN> 

   F
   f1178 reute
r f BC-BALDWIN-PIANO-&lt;BPAO&gt;   04-01 0070</UNKNOWN>
<TEXT> 
<TITLE>BALDWIN PIANO &lt;BPAO&gt; FILES SECONDARY OFFERING</TITLE>
<DATELINE>    CINCINNATI, April 1 - </DATELINE><BODY>Baldwin Piano and Organ Co said it
filed a registration statement covering a proposed public
offering of 630,000 common shares.
    Of the shares being offered, 490,000 shares will be sold by
General Electric Credit Corp and 140,000 by other shareholders.
    William Blair and Co and McDonald and Co will manage the
underwriting group, Baldwin said.
 Reuter
 </BODY></TEXT>
</REUTERS>