<?xml version="1.0" encoding="UTF-8"?><REUTERS CGISPLIT="TRAINING-SET" LEWISSPLIT="TRAIN" NEWID="5308" OLDID="10221" TOPICS="YES">
<DATE>16-MAR-1987 08:59:45.21</DATE>
<TOPICS><D>earn</D></TOPICS>
<PLACES><D>usa</D></PLACES>
<PEOPLE/>
<ORGS/>
<EXCHANGES/>
<COMPANIES/>
<UNKNOWN> 
   F
   f1898 reute
r f BC-AMERICAN-BUILDING-MAI   03-16 0036</UNKNOWN>
<TEXT> 
<TITLE>AMERICAN BUILDING MAINTENANCE &lt;ABM&gt; 1ST QTR NET</TITLE>
<DATELINE>    SAN FRANCISCO, March 16 -
    </DATELINE><BODY>Shr 35 cts vs 44 cts
    Net 1,311,000 vs 1,619,000
    Revs 125.2 mln vs 117.2 mln
    NOTE: American Building Maintenance Industries Inc.
 Reuter
 </BODY></TEXT>
</REUTERS>