<?xml version="1.0" encoding="UTF-8"?><REUTERS CGISPLIT="TRAINING-SET" LEWISSPLIT="TRAIN" NEWID="5579" OLDID="10492" TOPICS="YES">
<DATE>16-MAR-1987 14:03:23.38</DATE>
<TOPICS><D>earn</D></TOPICS>
<PLACES><D>usa</D></PLACES>
<PEOPLE/>
<ORGS/>
<EXCHANGES/>
<COMPANIES/>
<UNKNOWN> 
   F
   f3196 reute
r f BC-HARRIS-TEETER-PROPERT   03-16 0052</UNKNOWN>
<TEXT> 
<TITLE>HARRIS-TEETER PROPERTIES &lt;HTP&gt; REPORTS EARNINGS</TITLE>
<DATELINE>    CHARLOTTE, N.C., March 16 - </DATELINE><BODY>Harris-Teeter Properties Inc
reported fourth quarter fiscal 1986 earnings per share of 24
cts on earnings of 601,000 dlrs. 
    The realty investment trust company started operations in
August and had no comparable figures, it said.
 Reuter
 </BODY></TEXT>
</REUTERS>