<?xml version="1.0" encoding="UTF-8"?><REUTERS CGISPLIT="TRAINING-SET" LEWISSPLIT="TRAIN" NEWID="5669" OLDID="10582" TOPICS="YES">
<DATE>16-MAR-1987 16:06:07.34</DATE>
<TOPICS><D>earn</D></TOPICS>
<PLACES><D>canada</D></PLACES>
<PEOPLE/>
<ORGS/>
<EXCHANGES/>
<COMPANIES/>
<UNKNOWN> 
   E F
   f3537 reute
d f BC-&lt;canadian-roxy-petrol   03-16 0030</UNKNOWN>
<TEXT> 
<TITLE>&lt;CANADIAN ROXY PETROLEUM LTD&gt; YEAR NET</TITLE>
<DATELINE>    Calgary, Alberta, March 16 -
    </DATELINE><BODY>Shr profit five cts vs loss 23 cts
    Net profit 916,000 vs loss 2,886,000
    Revs 20.0 mln vs 28.2 mln
 Reuter
 </BODY></TEXT>
</REUTERS>