<?xml version="1.0" encoding="UTF-8"?><REUTERS CGISPLIT="TRAINING-SET" LEWISSPLIT="TRAIN" NEWID="5897" OLDID="10810" TOPICS="NO">
<DATE>17-MAR-1987 09:08:37.72</DATE>
<TOPICS/>
<PLACES><D>usa</D></PLACES>
<PEOPLE/>
<ORGS/>
<EXCHANGES><D>nyse</D></EXCHANGES>
<COMPANIES/>
<UNKNOWN> 
   F
   f4840 reute
r f BC-TANDEM-&lt;TNDM&gt;-APPLIES   03-17 0042</UNKNOWN>
<TEXT> 
<TITLE>TANDEM &lt;TNDM&gt; APPLIES FOR NYSE LISTING</TITLE>
<DATELINE>    CUPERTINO, Calif., March 17 - </DATELINE><BODY>Tandem Computers Inc said it
has applied for a New York Stock Exchange listing and expects
to start trading there by mid-April.
    Tandem's stock is now traded on the NASDAQ system.
 Reuter
 </BODY></TEXT>
</REUTERS>