<?xml version="1.0" encoding="UTF-8"?><REUTERS CGISPLIT="TRAINING-SET" LEWISSPLIT="TRAIN" NEWID="1512" OLDID="17930" TOPICS="YES">
<DATE> 4-MAR-1987 10:55:45.44</DATE>
<TOPICS><D>acq</D></TOPICS>
<PLACES><D>usa</D></PLACES>
<PEOPLE/>
<ORGS/>
<EXCHANGES/>
<COMPANIES/>
<UNKNOWN> 
   A RM F
   f0509 reute
r f BC-MARINE-MIDLAND-&lt;MM&gt;-B   03-04 0066</UNKNOWN>
<TEXT> 
<TITLE>MARINE MIDLAND &lt;MM&gt; BUYS BROKERAGE ASSETS</TITLE>
<DATELINE>    NEW YORK, March 4 - </DATELINE><BODY>Marine Midland Banks Inc said it has
acquired the customer account base of New York discount
brokerage firm Ovest Financial Services Inc for undisclosed
terms to expand its discount brokerage operations in the
Northeastern U.S.
    It said it will combine Ovest's activities with those of
its Marine Midland Brokerage Service unit.
 Reuter
 </BODY></TEXT>
</REUTERS>