<?xml version="1.0" encoding="UTF-8"?><REUTERS CGISPLIT="TRAINING-SET" LEWISSPLIT="TEST" NEWID="21522" OLDID="19914" TOPICS="NO">
<DATE>19-OCT-1987 06:54:39.85</DATE>
<TOPICS/>
<PLACES><D>singapore</D></PLACES>
<PEOPLE/>
<ORGS/>
<EXCHANGES/>
<COMPANIES/>
<UNKNOWN> 
   RM 
   f0508 reute
u f BC-SINGAPORE'S-RAFFLES-C   10-19 0080</UNKNOWN>
<TEXT> 
<TITLE>SINGAPORE'S RAFFLES CITY SIGNS 500 MLN DLR NIF</TITLE>
<DATELINE>    SINGAPORE, Oct 19 - </DATELINE><BODY>&lt;Raffles City Pte Ltd&gt; said it signed a
10 year note issuance facility (NIF) on Monday to raise 500 mln
Singapore dlrs.
    Proceeds of the issue would enable Raffles City to tap
cheaper funds from the market to refinance its existing
borrowings, a press statement said.
    The NIF is lead managed by two major local banks, the
Development Bank Of Singapore Ltd and the Overseas Chinese
Banking Corp.
 REUTER
 </BODY></TEXT>
</REUTERS>