<?xml version="1.0" encoding="UTF-8"?><REUTERS CGISPLIT="TRAINING-SET" LEWISSPLIT="TRAIN" NEWID="2006" OLDID="18424" TOPICS="YES">
<DATE> 5-MAR-1987 09:23:44.74</DATE>
<TOPICS><D>copper</D></TOPICS>
<PLACES><D>chile</D></PLACES>
<PEOPLE/>
<ORGS/>
<EXCHANGES/>
<COMPANIES/>
<UNKNOWN> 
   C M
   f0022 reute
b f BC-NO-QUAKE-DAMAGE-AT-CH   03-05 0089</UNKNOWN>
<TEXT> 
<TITLE>NO QUAKE DAMAGE AT CHUQUICAMATA - MINE SPOKESMAN</TITLE>
<DATELINE>    SANTIAGO, March 5 - </DATELINE><BODY>The earthquake which hit northern Chile
today, registering 7.0 on the open-ended Richter scale, caused
no damage to the copper mine at Chuquicamata, a mine spokesman
said.
    Chuquicamata public relations director Guillermo Barcelo
told Reuters by telephone from the mine that the quake had
caused no problems and operations continued as usual.
    A spokesman for the state Chilean Copper Commission in
Santiago confirmed there had been no damage at Chuquicamata.
 Reuter
 </BODY></TEXT>
</REUTERS>