<?xml version="1.0" encoding="UTF-8"?><REUTERS CGISPLIT="TRAINING-SET" LEWISSPLIT="TRAIN" NEWID="2120" OLDID="18538" TOPICS="NO">
<DATE> 5-MAR-1987 10:59:25.70</DATE>
<TOPICS/>
<PLACES><D>usa</D></PLACES>
<PEOPLE/>
<ORGS/>
<EXCHANGES/>
<COMPANIES/>
<UNKNOWN> 
   F
   f0455 reute
r f BC-NEECO-&lt;NEEC&gt;-SHARE-OF   03-05 0060</UNKNOWN>
<TEXT> 
<TITLE>NEECO &lt;NEEC&gt; SHARE OFFERING UNDER WAY</TITLE>
<DATELINE>    NEW YORK, March 5 - </DATELINE><BODY>Moseley Holdings Corp &lt;MOSE&gt; said an
offering of 1,700,000 common shares of NEECO Inc is under way
at 18.25 dlrs each.
    The company is selling 1,200,000 of the shares and
shareholders the rest.  The shareholders have granted
underwriters an overallotment option to buy up to 255,000 more
shares.
 Reuter
 </BODY></TEXT>
</REUTERS>