<?xml version="1.0" encoding="UTF-8"?><REUTERS CGISPLIT="TRAINING-SET" LEWISSPLIT="TRAIN" NEWID="2295" OLDID="18713" TOPICS="YES">
<DATE> 5-MAR-1987 13:19:00.24</DATE>
<TOPICS/>
<PLACES><D>usa</D></PLACES>
<PEOPLE/>
<ORGS/>
<EXCHANGES/>
<COMPANIES/>
<UNKNOWN> 
   F
   f0177 reute
d f BC-PROPOSED-OFFERINGS   03-05 0072</UNKNOWN>
<TEXT> 
<TITLE>PROPOSED OFFERINGS RECENTLY FILED WITH THE SEC</TITLE>
<DATELINE>    WASHINGTON, March 5 - </DATELINE><BODY>The following proposed securities
offerings were filed recently with the Securities and Exchange
Commission:
    Audiotronics Corp &lt;ADO&gt; - Shelf offering of up to five mln
dlrs of convertible subordinated debentures due 2002 through
H.J. Meyers and Co Inc.
    Georgia Gulf Corp &lt;GGLF&gt; - Offering of four mln shares of
common stock through Goldman, Sachs and Co.
 Reuter
 </BODY></TEXT>
</REUTERS>