<?xml version="1.0" encoding="UTF-8"?><REUTERS CGISPLIT="TRAINING-SET" LEWISSPLIT="TRAIN" NEWID="2572" OLDID="18990" TOPICS="YES">
<DATE> 6-MAR-1987 09:38:52.98</DATE>
<TOPICS><D>hog</D><D>livestock</D></TOPICS>
<PLACES><D>usa</D></PLACES>
<PEOPLE/>
<ORGS/>
<EXCHANGES><D>cme</D></EXCHANGES>
<COMPANIES/>
<UNKNOWN> 
   C L
   f0126 reute
u f BC-slaughter-guesstimate   03-06 0089</UNKNOWN>
<TEXT> 
<TITLE>HOG AND CATTLE SLAUGHTER GUESSTIMATES</TITLE>
<DATELINE>    CHICAGO, March 6 - </DATELINE><BODY>Chicago Mercantile Exchange floor
traders and commission house representatives are guesstimating
today's hog slaughter at about 300,000 to 305,000 head versus
292,000 week ago and 316,000 a year ago.
    Saturday's hog slaughter is guesstimated at about 30,000 to
55,000 head.
    Cattle slaughter is guesstimated at about 128,000 to
130,000 head versus 129,000 week ago and 119,000 a year ago.
    Saturday's cattle slaughter is guesstimated at about 20,000
to 40,000 head.
 Reuter
 </BODY></TEXT>
</REUTERS>