<?xml version="1.0" encoding="UTF-8"?><REUTERS CGISPLIT="TRAINING-SET" LEWISSPLIT="TRAIN" NEWID="3106" OLDID="19521" TOPICS="NO">
<DATE> 9-MAR-1987 10:40:29.63</DATE>
<TOPICS/>
<PLACES><D>usa</D></PLACES>
<PEOPLE/>
<ORGS/>
<EXCHANGES/>
<COMPANIES/>
<UNKNOWN> 
   F
   f0333 reute
d f BC-CAMBRIDGE-MEDICAL-&lt;CM   03-09 0094</UNKNOWN>
<TEXT> 
<TITLE>CAMBRIDGE MEDICAL &lt;CMTC&gt; ADDS INFO ON AIDS TEST</TITLE>
<DATELINE>    BILLERICA, Mass., March 9 - </DATELINE><BODY>Cambridge Medical Technology
Corp said pursuant to a letter of intent signed between it and
&lt;Panbaxy Laboratories&gt;, an AIDS test will be jointly
manufactured by the two companies.
    Cambridge said that before the test may be used for human
clinical purposes, it must undergo extensive clinical and human
testing and receive approval for marketing from the U.S. Food
and Drug Administration.
    The company said it is unable at this time to predict when
the test will become available.
 Reuter
 </BODY></TEXT>
</REUTERS>