<?xml version="1.0" encoding="UTF-8"?><REUTERS CGISPLIT="TRAINING-SET" LEWISSPLIT="TRAIN" NEWID="6912" OLDID="11825" TOPICS="YES">
<DATE>18-MAR-1987 18:05:22.64</DATE>
<TOPICS><D>coffee</D></TOPICS>
<PLACES><D>brazil</D><D>nicaragua</D></PLACES>
<PEOPLE/>
<ORGS/>
<EXCHANGES/>
<COMPANIES/>
<UNKNOWN> 
   C T
   f9713 reute
u f BC-IBC-PRESIDENT-TO-ATTE   03-18 0076</UNKNOWN>
<TEXT> 
<TITLE>IBC PRESIDENT TO ATTEND MANAGUA COFFEE MEETING</TITLE>
<DATELINE>    RIO DE JANEIRO, MARCH 18 - </DATELINE><BODY>Brazilian Coffee Institute (IBC)
president Jorio Dauster said he will attend a meeting in
Managua this weekend.
    He told Reuters by telephone from Brasilia that the
meeting, involving Brazil, Colombia and Central American coffee
producers, will be strictly to review the coffee market
situation.
    "The meeting is set for Saturday but could also continue on
Sunday," he said.
 Reuter
 </BODY></TEXT>
</REUTERS>