<?xml version="1.0" encoding="UTF-8"?><REUTERS CGISPLIT="TRAINING-SET" LEWISSPLIT="TEST" NEWID="20553" OLDID="21148" TOPICS="NO">
<DATE>20-OCT-1987 14:29:53.07</DATE>
<TOPICS/>
<PLACES><D>usa</D></PLACES>
<PEOPLE/>
<ORGS/>
<EXCHANGES/>
<COMPANIES/>
<UNKNOWN> 
   F 
   f2704 reute
s f BC-LOEWS-CORP-&lt;LTR&gt;-SETS   10-20 0020</UNKNOWN>
<TEXT> 
<TITLE>LOEWS CORP &lt;LTR&gt; SETS QUARTERLY</TITLE>
<DATELINE>    NEW YORK, Oct 20 -
    </DATELINE><BODY>Qtly div 25 cts vs 25 cts prior
    Pay Dec One
    Record Nov 12
 Reuter
 </BODY></TEXT>
</REUTERS>