<?xml version="1.0" encoding="UTF-8"?><REUTERS CGISPLIT="TRAINING-SET" LEWISSPLIT="TRAIN" NEWID="4348" OLDID="9261" TOPICS="NO">
<DATE>12-MAR-1987 12:57:12.92</DATE>
<TOPICS/>
<PLACES><D>usa</D></PLACES>
<PEOPLE/>
<ORGS/>
<EXCHANGES/>
<COMPANIES/>
<UNKNOWN> 
   F
   f0814 reute
r f BC-CENTURY-&lt;CTL&gt;-TO-SELL   03-12 0096</UNKNOWN>
<TEXT> 
<TITLE>CENTURY &lt;CTL&gt; TO SELL CABLE PROPERTIES</TITLE>
<DATELINE>    MONROE, La., March 12 - </DATELINE><BODY>Century Telephone Enterprises Inc
said it agreed to sell its cable television properties located
in Michigan, Tennesse, Tennesse, Florida, Arkansas and
Louisiana.
    Terms and the name of the purchaser were not disclosed.
    The transaction, subject to a definitive agreement, is
expected to be completed in the near future, it said.
    Century said it expects to recognize a substantial gain on
the sale. For the year ended December 31, Century reported net
income of 17.2 mln dlrs on sales 146.0 mln dlrs.

 Reuter
 </BODY></TEXT>
</REUTERS>