<?xml version="1.0" encoding="UTF-8"?><REUTERS CGISPLIT="TRAINING-SET" LEWISSPLIT="TEST" NEWID="19870" OLDID="8198" TOPICS="YES">
<DATE>29-JUN-1987 15:44:11.58</DATE>
<TOPICS><D>acq</D></TOPICS>
<PLACES><D>usa</D></PLACES>
<PEOPLE/>
<ORGS/>
<EXCHANGES/>
<COMPANIES/>
<UNKNOWN> 
   F 
   f2357 reute
d f BC-CYCARE-SYSTEMS-INC-&lt;C   06-29 0078</UNKNOWN>
<TEXT> 
<TITLE>CYCARE SYSTEMS INC &lt;CYCR&gt; BUYS MEDTEC</TITLE>
<DATELINE>    PHOENIX, Ariz, June 29 - </DATELINE><BODY>CyCare Systems Inc said it bought
Control Data Corp's &lt;CDA&gt; MedTec unit for an undisclosed sum.
    The company said MedTec's new client base could have a
significant impact on long-term revenues, although it expects a
minimal positive impact on earnings in the next six months.
    It said the assets purchased include processing agreements,
software maintenance contracts and the supporting software.
 Reuter
 </BODY></TEXT>
</REUTERS>