<?xml version="1.0" encoding="UTF-8"?><REUTERS CGISPLIT="TRAINING-SET" LEWISSPLIT="TEST" NEWID="15249" OLDID="4499" TOPICS="YES">
<DATE> 8-APR-1987 15:13:12.58</DATE>
<TOPICS/>
<PLACES><D>usa</D></PLACES>
<PEOPLE/>
<ORGS/>
<EXCHANGES/>
<COMPANIES/>
<UNKNOWN> 
   F
   f2267 reute
h f BC-&lt;NSA-INC&gt;-OFFERS-TO-R   04-08 0104</UNKNOWN>
<TEXT> 
<TITLE>&lt;NSA INC&gt; OFFERS TO REPURCHASE OWN SHARES</TITLE>
<DATELINE>    CHERRY HILL, N.J., April 8 - </DATELINE><BODY>NSA Inc said, in an attempt to
go private and repurchase its shares, it is offering to
exchange a five year subordinated investment note for each
share held by shareholders with more than 600 shares.
    NSA said the investment note will carry a face value of one
dlr and will pay five annual principal installments, as well as
quarterly interest payments on the outstanding principal amount
at an eight pct annual rate.
    NSA added that for shareholders with less than 600 shares
it is offering to purchase their shares for cash at one dlr per
share.
 Reuter
 </BODY></TEXT>
</REUTERS>