<?xml version="1.0" encoding="UTF-8"?><REUTERS CGISPLIT="TRAINING-SET" LEWISSPLIT="TEST" NEWID="15361" OLDID="4344" TOPICS="NO">
<DATE> 8-APR-1987 17:46:26.17</DATE>
<TOPICS/>
<PLACES><D>usa</D></PLACES>
<PEOPLE/>
<ORGS/>
<EXCHANGES/>
<COMPANIES/>
<UNKNOWN> 
   F
   f2725 reute
r f BC-INVESTOR-CHARGES-WITH   04-08 0109</UNKNOWN>
<TEXT> 
<TITLE>INVESTOR CHARGES WITH STOCK MANUPULATION</TITLE>
<DATELINE>    NEW YORK, April 8 - </DATELINE><BODY>William Rodman, a 43-year-old New York
investor was indicted for allegedly plotting to manipulate the
price of three over-the-counter stocks to drive up their prices
and create interest in the companies.
    Rodman was also charged with securities and wire fraud
stemming from the alleged manipulation of the stocks of Memory
Metals Inc &lt;MRMT&gt;, Memory Protection Devices Inc &lt;MPDI&gt; and
&lt;Intravision Inc&gt;, beginning in January 1984.
    The indictment charged that Rodman and other unnamed
co-conspirators bought and sold the stocks through 100 accounts
in at least 35 broker-dealer firms.
   
 Reuter
 </BODY></TEXT>
</REUTERS>