<?xml version="1.0" encoding="UTF-8"?><REUTERS CGISPLIT="TRAINING-SET" LEWISSPLIT="TEST" NEWID="15628" OLDID="5526" TOPICS="YES">
<DATE> 9-APR-1987 11:14:08.90</DATE>
<TOPICS/>
<PLACES><D>usa</D></PLACES>
<PEOPLE/>
<ORGS/>
<EXCHANGES/>
<COMPANIES/>
<UNKNOWN> 

   F
   f1289 reute
r f BC-K-MART-&lt;KM&gt;-OPENS-BAN   04-09 0062</UNKNOWN>
<TEXT> 
<TITLE>K MART &lt;KM&gt; OPENS BANK BRANCHES IN STORES</TITLE>
<DATELINE>    TAMPA, Fla., April 9 - </DATELINE><BODY>K Mart Corp said it was opening
branch offices of &lt;First Nationwide Bank&gt; in 21 of its stores
in Florida.
    The company said this brings to 57 the number of bank
branch, which are part of the Nationwide Network, an alliance
of 40 independent locally managed financial institutions,
locations in Florida.
 Reuter
 </BODY></TEXT>
</REUTERS>