<?xml version="1.0" encoding="UTF-8"?><REUTERS CGISPLIT="TRAINING-SET" LEWISSPLIT="TRAIN" NEWID="8353" OLDID="13874" TOPICS="YES">
<DATE>23-MAR-1987 11:53:00.98</DATE>
<TOPICS><D>acq</D></TOPICS>
<PLACES><D>usa</D></PLACES>
<PEOPLE/>
<ORGS/>
<EXCHANGES/>
<COMPANIES/>
<UNKNOWN> 
   F
   f1481 reute
r f BC-DWG-&lt;DWG&gt;-COMPLETES-S   03-23 0056</UNKNOWN>
<TEXT> 
<TITLE>DWG &lt;DWG&gt; COMPLETES SALE OF UNIT</TITLE>
<DATELINE>    MIAMI, March 23 - </DATELINE><BODY>DWG Corp said it has completed the
previously-announced sale of its Texsun Corp subsidiary to
Texsun Corp subsidiary to Sundor Brands Inc for 27.5 mln dlrs
and the assumption of liabilities.
    It said proceeds have been placed in escrow pending the
outcome of talks with lenders.
 Reuter
 </BODY></TEXT>
</REUTERS>