<?xml version="1.0" encoding="UTF-8"?><REUTERS CGISPLIT="TRAINING-SET" LEWISSPLIT="TRAIN" NEWID="12095" OLDID="323" TOPICS="YES">
<DATE> 1-APR-1987 12:43:09.50</DATE>
<TOPICS/>
<PLACES><D>usa</D></PLACES>
<PEOPLE/>
<ORGS/>
<EXCHANGES/>
<COMPANIES/>
<UNKNOWN> 

   F
   f1706 reute
w f BC-DIAMOND-STAR-MOTORS-N   04-01 0080</UNKNOWN>
<TEXT> 
<TITLE>DIAMOND-STAR MOTORS NAMES ADDITIONAL SUPPLIERS</TITLE>
<DATELINE>    BLOOMINGTON, ILL., April 1 - </DATELINE><BODY>Diamond-Star Motors Corp, the
joint-venture company owned by Chrysler Corp &lt;C&gt; and Mitsubishi
Motors, named additional production suppliers for the new
vehicle to be produced at the company's plant under
construction in Bloomington, Ill.
    It said Amtex Inc, Sidney, Ohio, was selected to supply
trunk floor carpets and Bluewater Plastics Inc, Marysville,
Mich., duct assemblies and column covers.
 Reuter
 </BODY></TEXT>
</REUTERS>