<?xml version="1.0" encoding="UTF-8"?><REUTERS CGISPLIT="TRAINING-SET" LEWISSPLIT="TRAIN" NEWID="12988" OLDID="1957" TOPICS="YES">
<DATE> 3-APR-1987 12:29:08.38</DATE>
<TOPICS><D>acq</D></TOPICS>
<PLACES><D>usa</D></PLACES>
<PEOPLE/>
<ORGS/>
<EXCHANGES/>
<COMPANIES/>
<UNKNOWN> 

   F
   f1620 reute
r f BC-OCCIDENTAL-&lt;OXY&gt;-UNIT   04-03 0063</UNKNOWN>
<TEXT> 
<TITLE>OCCIDENTAL &lt;OXY&gt; UNIT SELLS DIVISION</TITLE>
<DATELINE>    DARIEN, Conn, APril 3 - </DATELINE><BODY>Occidental Petroleum Corp's
Occidental Chemcial Corp said it sold the Process chemicals
division it acquired as part of the September 1986  purchase of
Diamond Shamrock Chemicals to Henkel KGAA of Dusseldorf, West
Germany.
    Terms were not disclosed.
    The division makes specialty industrial chemicals, it said.
    Later, industry sources said the division, which had
worldwide sales of some 160 mln dlrs last year, was sold for
just under 200 mln dlrs.
 Reuter
 </BODY></TEXT>
</REUTERS>